setup.py
django_hitcount_mixed_object.egg-info/PKG-INFO
django_hitcount_mixed_object.egg-info/SOURCES.txt
django_hitcount_mixed_object.egg-info/dependency_links.txt
django_hitcount_mixed_object.egg-info/top_level.txt
hitcount_mixed_object/__init__.py
hitcount_mixed_object/api.py
hitcount_mixed_object/conf.py
hitcount_mixed_object/models.py
hitcount_mixed_object/backends/__init__.py
hitcount_mixed_object/backends/mongodb.py
hitcount_mixed_object/management/__init__.py
hitcount_mixed_object/management/commands/__init__.py
hitcount_mixed_object/management/commands/clear_hitcount_collection.py