Metadata-Version: 1.0
Name: django-hitcount-mixed-object
Version: 0.1.1
Summary: holds hit count of mixed objects represented at relation model using NoSQL db
Home-page: https://github.com/rmaceissoft/django-hitcount-mixed-object
Author: Reiner Marquez
Author-email: rmaceissoft@gmail.com
License: UNKNOWN
Platform: UNKNOWN
Classifier: Development Status :: 4 - Beta
Classifier: Environment :: Console
Classifier: Framework :: Django
Classifier: Intended Audience :: Developers
Classifier: Intended Audience :: Information Technology
Classifier: License :: OSI Approved :: BSD License
Classifier: Operating System :: OS Independent
Classifier: Programming Language :: Python
